zs_amazon_scraper/__init__.py
zs_amazon_scraper/amazon.py
zs_amazon_scraper/helpers/__init__.py
zs_amazon_scraper/helpers/parser.py
zs_amazon_scraper/utils/__init__.py
zs_amazon_scraper/utils/url_creator.py
zs_amazon_scraper/utils/utils.py
zs_amazon_scraper-0.2.8.dist-info/METADATA
zs_amazon_scraper-0.2.8.dist-info/WHEEL
zs_amazon_scraper-0.2.8.dist-info/top_level.txt
zs_amazon_scraper-0.2.8.dist-info/RECORD
