Metadata-Version: 2.1
Name: zs-amazon-scraper
Version: 0.2.8
Summary: amazon_scraper
Home-page: https://github.com/kkristof200/amazon_scraper
Author: Kovács Kristóf-Attila and Péntek Zsolt
License: UNKNOWN
Platform: UNKNOWN
Classifier: Programming Language :: Python :: 3
Classifier: License :: OSI Approved :: MIT License
Classifier: Operating System :: OS Independent
Requires-Python: >=3.6
Requires-Dist: kcu
Requires-Dist: beautifulsoup4
